pybbm_private_messages-0.3.1.dist-info/metadata.json
pybbm_private_messages-0.3.1.dist-info/top_level.txt
pybbm_private_messages-0.3.1.dist-info/METADATA
pybbm_private_messages-0.3.1.dist-info/WHEEL
pybbm_private_messages-0.3.1.dist-info/pbr.json
pybbm_private_messages-0.3.1.dist-info/RECORD
pybbm_private_messages-0.3.1.dist-info/DESCRIPTION.rst
private_messages/views.py
private_messages/models.py
private_messages/__init__.py
private_messages/tests.py
private_messages/forms.py
private_messages/admin.py
private_messages/urls.py
private_messages/context_processors.py
private_messages/templates/pybb/post_template.html
private_messages/templates/pybb/base.html
private_messages/templates/pybb/private_messages/message.html
private_messages/templates/pybb/private_messages/links.html
private_messages/templates/pybb/private_messages/form.html
private_messages/templates/pybb/private_messages/new.html
private_messages/templates/pybb/private_messages/confirm_delete.html
private_messages/templates/pybb/private_messages/inbox.html
private_messages/templatetags/__init__.py
private_messages/templatetags/private_messages.py
private_messages/migrations/__init__.py
private_messages/migrations/0001_initial.py
